predictr.py
predictr-0.1.30.dist-info/LICENSE.txt
predictr-0.1.30.dist-info/METADATA
predictr-0.1.30.dist-info/WHEEL
predictr-0.1.30.dist-info/top_level.txt
predictr-0.1.30.dist-info/RECORD
