Metadata-Version: 2.1
Name: predictr
Version: 0.1.30
Summary: Life Data Analysis for Reliability Engineers - Weibull Analysis, Detailed Plots, Compute Statistics
Home-page: https://tvtoglu.github.io/predictr/
Author: Tamer Tevetoglu
Author-email: predictr@outlook.com
License: UNKNOWN
Project-URL: Documentation, https://tvtoglu.github.io/predictr/classes/
Project-URL: GitHub, https://github.com/tvtoglu/predictr
Project-URL: Github Discussions, https://github.com/tvtoglu/predictr/discussions
Keywords: reliability,weibull,bias,life data analysis,engineering,confidence,bootstrap,monte-carlo,fisher bounds,likelihood ratio,unreliability,survival analysis,lifelines,testing
Platform: UNKNOWN
Classifier: Programming Language :: Python :: 3
Classifier: Programming Language :: Python :: 3.6
Classifier: Programming Language :: Python :: 3.7
Classifier: Programming Language :: Python :: 3.8
Classifier: Programming Language :: Python :: 3.9
Classifier: Programming Language :: Python :: 3.10
Classifier: Programming Language :: Python :: 3.11
Classifier: Programming Language :: Python :: 3.12
Classifier: Programming Language :: Python :: 3.13
Classifier: License :: OSI Approved :: MIT License
Classifier: Operating System :: OS Independent
License-File: LICENSE.txt
Requires-Dist: numpy (>=1.16.0)
Requires-Dist: scipy (>=1.3.0)
Requires-Dist: pandas (>=1.0.0)
Requires-Dist: matplotlib (>=2.2.0)
